s3stat
