Metadata-Version: 1.0
Name: s3stat
Version: 2.1.0
Summary: An extensible Amazon S3 and Cloudfront log parser.
Home-page: https://github.com/nagyv/s3stat
Author: Viktor Nagy
Author-email: v@pulilab.com
License: UNKNOWN
Keywords: s3stat amazon statistics goaccess
Platform: UNKNOWN
